README.md
setup.cfg
setup.py
pyfi/__init__.py
pyfi/bondanalysis.py
pyfi/mapper.py
pyfi/valuation.py
pyfi/wind_helper.py
pyfi/wind_helper_test.py
pyfixedincome.egg-info/PKG-INFO
pyfixedincome.egg-info/SOURCES.txt
pyfixedincome.egg-info/dependency_links.txt
pyfixedincome.egg-info/top_level.txt
pyfixedincome.egg-info/zip-safe