Metadata-Version: 1.0
Name: pyfixedincome
Version: 0.1.0
Summary: encapsulate the windPy API with pandas
Home-page: https://github.com/wangluzhou/pyfi.git
Author: wangluzhou
Author-email: wangluzhou@aliyun.com
License: MIT
Platform: UNKNOWN
